README.md
setup.py
ahocorasick/__init__.py
ahocorasick_python.egg-info/PKG-INFO
ahocorasick_python.egg-info/SOURCES.txt
ahocorasick_python.egg-info/dependency_links.txt
ahocorasick_python.egg-info/top_level.txt