Metadata-Version: 2.1
Name: ahocorasick-python
Version: 0.0.7
Summary: this project is a aho-corasick automaton implementation by python
Home-page: https://github.com/zhoukunpeng504/ahocorasick-python
Author: zhoukunpeng
Author-email: zhoukunpeng504@163.com
License: UNKNOWN
Platform: UNKNOWN
